<?xml version="1.0" ?><annotation>
	<folder>BlackBerry</folder>
	<filename>44.jpg</filename>
	<source>
		<database>Unknown</database>
	</source>
	<size>
		<width>359</width>
		<height>496</height>
		<depth>3</depth>
	</size>
	<segmented>0</segmented>
	<object>
		<name>BlackBerry</name>
		<pose>Unspecified</pose>
		<truncated>0</truncated>
		<difficult>0</difficult>
		<bndbox>
			<xmin>124</xmin>
			<ymin>204</ymin>
			<xmax>227</xmax>
			<ymax>266</ymax>
		</bndbox>
	</object>
	<object>
		<name>BlackBerry</name>
		<pose>Unspecified</pose>
		<truncated>0</truncated>
		<difficult>0</difficult>
		<bndbox>
			<xmin>124</xmin>
			<ymin>263</ymin>
			<xmax>220</xmax>
			<ymax>289</ymax>
		</bndbox>
	</object>
</annotation>