<?xml version="1.0" ?><annotation verified="no">
	<folder>McLaren</folder>
	<filename>17.jpg</filename>
	<source>
		<database>Unknown</database>
	</source>
	<size>
		<width>514</width>
		<height>370</height>
		<depth>3</depth>
	</size>
	<segmented>0</segmented>
	<object>
		<name>mclaren</name>
		<pose>Unspecified</pose>
		<truncated>0</truncated>
		<difficult>0</difficult>
		<bndbox>
			<xmin>44</xmin>
			<ymin>209</ymin>
			<xmax>273</xmax>
			<ymax>257</ymax>
		</bndbox>
	</object>
	<object>
		<name>mclaren</name>
		<pose>Unspecified</pose>
		<truncated>0</truncated>
		<difficult>0</difficult>
		<bndbox>
			<xmin>329</xmin>
			<ymin>86</ymin>
			<xmax>476</xmax>
			<ymax>143</ymax>
		</bndbox>
	</object>
</annotation>